{
  "grade": 7,
  "subject": "Tiếng Anh",
  "subjectCode": "ENG7",
  "difficulty": "medium",
  "description": "Medium exercises for Grade 7 English (Lớp 7 Tiếng Anh) - standard practice",
  "lessons": [
    {
      "code": "ENG7-CH1-L1",
      "chapter": "My House and My School",
      "lessonTitle": "Rooms in the house",
      "exercises": [
        {
          "title": "Choose the best answer: There ______ a big kitchen in my house. (A) is (B) are (C) be",
          "type": "multiple_choice",
          "points": 2,
          "question": "Choose the best answer: There ______ a big kitchen in my house. (A) is (B) are (C) be",
          "options": {
            "A": "Đáp án A",
            "B": "Đáp án B (Đúng)",
            "C": "Đáp án C",
            "D": "Đáp án D"
          },
          "correctOption": "B",
          "hint": "Hãy suy nghĩ về Rooms in the house.",
          "created_at": "2025-01-01T00:00:00.000Z"
        },
        {
          "title": "Choose the best answer: There ______ two bedrooms upstairs. (A) is (B) are (C) am",
          "type": "multiple_choice",
          "points": 2,
          "question": "Choose the best answer: There ______ two bedrooms upstairs. (A) is (B) are (C) am",
          "options": {
            "A": "Đáp án A",
            "B": "Đáp án B (Đúng)",
            "C": "Đáp án C",
            "D": "Đáp án D"
          },
          "correctOption": "B",
          "hint": "Hãy suy nghĩ về Rooms in the house.",
          "created_at": "2025-01-01T00:00:01.000Z"
        },
        {
          "title": "Choose the best option: Our living room is on the ______ floor. (A) one (B) first (C) firstly",
          "type": "multiple_choice",
          "points": 2,
          "question": "Choose the best option: Our living room is on the ______ floor. (A) one (B) first (C) firstly",
          "options": {
            "A": "Đáp án A",
            "B": "Đáp án B (Đúng)",
            "C": "Đáp án C",
            "D": "Đáp án D"
          },
          "correctOption": "B",
          "hint": "Hãy suy nghĩ về Rooms in the house.",
          "created_at": "2025-01-01T00:00:02.000Z"
        },
        {
          "title": "Complete the sentence: The ______ has a sofa and a TV. (A) bedroom (B) living room (C) bathroom",
          "type": "multiple_choice",
          "points": 2,
          "question": "Complete the sentence: The ______ has a sofa and a TV. (A) bedroom (B) living room (C) bathroom",
          "options": {
            "A": "Đáp án A",
            "B": "Đáp án B (Đúng)",
            "C": "Đáp án C",
            "D": "Đáp án D"
          },
          "correctOption": "B",
          "hint": "Hãy suy nghĩ về Rooms in the house.",
          "created_at": "2025-01-01T00:00:03.000Z"
        },
        {
          "title": "Choose the correct form: There ______ many rooms in my house. (A) is (B) are (C) be",
          "type": "multiple_choice",
          "points": 2,
          "question": "Choose the correct form: There ______ many rooms in my house. (A) is (B) are (C) be",
          "options": {
            "A": "Đáp án A",
            "B": "Đáp án B (Đúng)",
            "C": "Đáp án C",
            "D": "Đáp án D"
          },
          "correctOption": "B",
          "hint": "Hãy suy nghĩ về Rooms in the house.",
          "created_at": "2025-01-01T00:00:04.000Z"
        },
        {
          "title": "Writing: Describe your house in 5–6 sentences (number of rooms, what is in each room, which room you like most and why).",
          "type": "essay",
          "points": 3,
          "question": "Writing: Describe your house in 5–6 sentences (number of rooms, what is in each room, which room you like most and why).",
          "hint": "Hãy viết về Rooms in the house.",
          "answer": "Đây là câu trả lời mẫu về Rooms in the house.",
          "created_at": "2025-01-01T00:00:05.000Z"
        },
        {
          "title": "Writing: Write a paragraph comparing your house with your friend's house. Use \"There is/There are\" and descriptive adjectives.",
          "type": "essay",
          "points": 3,
          "question": "Writing: Write a paragraph comparing your house with your friend's house. Use \"There is/There are\" and descriptive adjectives.",
          "hint": "Hãy viết về Rooms in the house.",
          "answer": "Đây là câu trả lời mẫu về Rooms in the house.",
          "created_at": "2025-01-01T00:00:06.000Z"
        }
      ]
    },
    {
      "code": "ENG7-CH1-L2",
      "chapter": "My House and My School",
      "lessonTitle": "Places at school",
      "exercises": [
        {
          "title": "Choose the best answer: Students usually have lunch in the ______. (A) library (B) canteen (C) classroom",
          "type": "multiple_choice",
          "points": 2,
          "question": "Choose the best answer: Students usually have lunch in the ______. (A) library (B) canteen (C) classroom",
          "options": {
            "A": "Đáp án A",
            "B": "Đáp án B (Đúng)",
            "C": "Đáp án C",
            "D": "Đáp án D"
          },
          "correctOption": "B",
          "hint": "Hãy suy nghĩ về Places at school.",
          "created_at": "2025-01-01T00:00:00.000Z"
        },
        {
          "title": "Choose the best answer: We can borrow books from the ______. (A) playground (B) gym (C) library",
          "type": "multiple_choice",
          "points": 2,
          "question": "Choose the best answer: We can borrow books from the ______. (A) playground (B) gym (C) library",
          "options": {
            "A": "Đáp án A",
            "B": "Đáp án B (Đúng)",
            "C": "Đáp án C",
            "D": "Đáp án D"
          },
          "correctOption": "B",
          "hint": "Hãy suy nghĩ về Places at school.",
          "created_at": "2025-01-01T00:00:01.000Z"
        },
        {
          "title": "Choose the correct sentence: (A) There are a big playground at my school. (B) There is a big playground at my school. (C) There be a big playground at my school.",
          "type": "multiple_choice",
          "points": 2,
          "question": "Choose the correct sentence: (A) There are a big playground at my school. (B) There is a big playground at my school. (C) There be a big playground at my school.",
          "options": {
            "A": "Đáp án A",
            "B": "Đáp án B (Đúng)",
            "C": "Đáp án C",
            "D": "Đáp án D"
          },
          "correctOption": "B",
          "hint": "Hãy suy nghĩ về Places at school.",
          "created_at": "2025-01-01T00:00:02.000Z"
        },
        {
          "title": "Complete: The science lab is ______ the second floor. (A) in (B) on (C) at",
          "type": "multiple_choice",
          "points": 2,
          "question": "Complete: The science lab is ______ the second floor. (A) in (B) on (C) at",
          "options": {
            "A": "Đáp án A",
            "B": "Đáp án B (Đúng)",
            "C": "Đáp án C",
            "D": "Đáp án D"
          },
          "correctOption": "B",
          "hint": "Hãy suy nghĩ về Places at school.",
          "created_at": "2025-01-01T00:00:03.000Z"
        },
        {
          "title": "Choose: We do experiments in the ______. (A) library (B) laboratory (C) canteen",
          "type": "multiple_choice",
          "points": 2,
          "question": "Choose: We do experiments in the ______. (A) library (B) laboratory (C) canteen",
          "options": {
            "A": "Đáp án A",
            "B": "Đáp án B (Đúng)",
            "C": "Đáp án C",
            "D": "Đáp án D"
          },
          "correctOption": "B",
          "hint": "Hãy suy nghĩ về Places at school.",
          "created_at": "2025-01-01T00:00:04.000Z"
        },
        {
          "title": "Writing: Write 5 sentences to describe your school (buildings, playground, library, canteen, etc.).",
          "type": "essay",
          "points": 3,
          "question": "Writing: Write 5 sentences to describe your school (buildings, playground, library, canteen, etc.).",
          "hint": "Hãy viết về Places at school.",
          "answer": "Đây là câu trả lời mẫu về Places at school.",
          "created_at": "2025-01-01T00:00:05.000Z"
        },
        {
          "title": "Writing: Write a paragraph about your favorite place at school and explain why you like it.",
          "type": "essay",
          "points": 3,
          "question": "Writing: Write a paragraph about your favorite place at school and explain why you like it.",
          "hint": "Hãy viết về Places at school.",
          "answer": "Đây là câu trả lời mẫu về Places at school.",
          "created_at": "2025-01-01T00:00:06.000Z"
        }
      ]
    },
    {
      "code": "ENG7-CH1-L3",
      "chapter": "My House and My School",
      "lessonTitle": "Present Simple – daily routine",
      "exercises": [
        {
          "title": "Choose the best answer: He ______ to school at 7 a.m. (A) go (B) goes (C) going",
          "type": "multiple_choice",
          "points": 2,
          "question": "Choose the best answer: He ______ to school at 7 a.m. (A) go (B) goes (C) going",
          "options": {
            "A": "Đáp án A",
            "B": "Đáp án B (Đúng)",
            "C": "Đáp án C",
            "D": "Đáp án D"
          },
          "correctOption": "B",
          "hint": "Hãy suy nghĩ về Present Simple – daily routine.",
          "created_at": "2025-01-01T00:00:00.000Z"
        }
      ]
    },
    {
      "code": "ENG7-CH2-L1",
      "chapter": "Health and Hobbies",
      "lessonTitle": "Health problems and advice",
      "exercises": [
        {
          "title": "Choose the best answer: I have a ______. I can't eat anything. (A) headache (B) toothache (C) stomachache",
          "type": "multiple_choice",
          "points": 2,
          "question": "Choose the best answer: I have a ______. I can't eat anything. (A) headache (B) toothache (C) stomachache",
          "options": {
            "A": "Đáp án A",
            "B": "Đáp án B (Đúng)",
            "C": "Đáp án C",
            "D": "Đáp án D"
          },
          "correctOption": "B",
          "hint": "Hãy suy nghĩ về Health problems and advice.",
          "created_at": "2025-01-01T00:00:00.000Z"
        },
        {
          "title": "Choose the best answer: You ______ drink more water. (A) should (B) shouldn't (C) mustn't",
          "type": "multiple_choice",
          "points": 2,
          "question": "Choose the best answer: You ______ drink more water. (A) should (B) shouldn't (C) mustn't",
          "options": {
            "A": "Đáp án A",
            "B": "Đáp án B (Đúng)",
            "C": "Đáp án C",
            "D": "Đáp án D"
          },
          "correctOption": "B",
          "hint": "Hãy suy nghĩ về Health problems and advice.",
          "created_at": "2025-01-01T00:00:01.000Z"
        },
        {
          "title": "Choose the best answer: He has a fever, so he ______ go to school today. (A) should (B) shouldn't (C) can",
          "type": "multiple_choice",
          "points": 2,
          "question": "Choose the best answer: He has a fever, so he ______ go to school today. (A) should (B) shouldn't (C) can",
          "options": {
            "A": "Đáp án A",
            "B": "Đáp án B (Đúng)",
            "C": "Đáp án C",
            "D": "Đáp án D"
          },
          "correctOption": "B",
          "hint": "Hãy suy nghĩ về Health problems and advice.",
          "created_at": "2025-01-01T00:00:02.000Z"
        },
        {
          "title": "Complete: I have a sore throat. I ______ see a doctor. (A) should (B) shouldn't (C) must",
          "type": "multiple_choice",
          "points": 2,
          "question": "Complete: I have a sore throat. I ______ see a doctor. (A) should (B) shouldn't (C) must",
          "options": {
            "A": "Đáp án A",
            "B": "Đáp án B (Đúng)",
            "C": "Đáp án C",
            "D": "Đáp án D"
          },
          "correctOption": "B",
          "hint": "Hãy suy nghĩ về Health problems and advice.",
          "created_at": "2025-01-01T00:00:03.000Z"
        },
        {
          "title": "Choose: You look tired. You ______ go to bed early. (A) should (B) shouldn't (C) can't",
          "type": "multiple_choice",
          "points": 2,
          "question": "Choose: You look tired. You ______ go to bed early. (A) should (B) shouldn't (C) can't",
          "options": {
            "A": "Đáp án A",
            "B": "Đáp án B (Đúng)",
            "C": "Đáp án C",
            "D": "Đáp án D"
          },
          "correctOption": "B",
          "hint": "Hãy suy nghĩ về Health problems and advice.",
          "created_at": "2025-01-01T00:00:04.000Z"
        },
        {
          "title": "Writing: Write 4–5 sentences giving advice to a friend who has a cold (using \"should\" and \"shouldn't\").",
          "type": "essay",
          "points": 3,
          "question": "Writing: Write 4–5 sentences giving advice to a friend who has a cold (using \"should\" and \"shouldn't\").",
          "hint": "Hãy viết về Health problems and advice.",
          "answer": "Đây là câu trả lời mẫu về Health problems and advice.",
          "created_at": "2025-01-01T00:00:05.000Z"
        },
        {
          "title": "Writing: Write a paragraph about what you should and shouldn't do to stay healthy.",
          "type": "essay",
          "points": 3,
          "question": "Writing: Write a paragraph about what you should and shouldn't do to stay healthy.",
          "hint": "Hãy viết về Health problems and advice.",
          "answer": "Đây là câu trả lời mẫu về Health problems and advice.",
          "created_at": "2025-01-01T00:00:06.000Z"
        },
        {
          "title": "Phân tích về Health problems and advice",
          "type": "multiple_choice",
          "points": 2,
          "question": "Phân tích về Health problems and advice (Câu 15/15)",
          "options": {
            "A": "Option A",
            "B": "Option B (Correct)",
            "C": "Option C",
            "D": "Option D"
          },
          "correctOption": "B",
          "hint": "Vận dụng kiến thức đã học về Health problems and advice để trả lời.",
          "created_at": "2025-01-01T00:00:14.000Z"
        }
      ]
    },
    {
      "code": "ENG7-CH2-L2",
      "chapter": "Health and Hobbies",
      "lessonTitle": "Talking about hobbies",
      "exercises": [
        {
          "title": "Choose the best answer: My favourite ______ is playing badminton. (A) hobby (B) job (C) food",
          "type": "multiple_choice",
          "points": 2,
          "question": "Choose the best answer: My favourite ______ is playing badminton. (A) hobby (B) job (C) food",
          "options": {
            "A": "Đáp án A",
            "B": "Đáp án B (Đúng)",
            "C": "Đáp án C",
            "D": "Đáp án D"
          },
          "correctOption": "B",
          "hint": "Hãy suy nghĩ về Talking about hobbies.",
          "created_at": "2025-01-01T00:00:00.000Z"
        },
        {
          "title": "Choose the best answer: I ______ collecting stamps. (A) am interested in (B) am interested (C) interested in",
          "type": "multiple_choice",
          "points": 2,
          "question": "Choose the best answer: I ______ collecting stamps. (A) am interested in (B) am interested (C) interested in",
          "options": {
            "A": "Đáp án A",
            "B": "Đáp án B (Đúng)",
            "C": "Đáp án C",
            "D": "Đáp án D"
          },
          "correctOption": "B",
          "hint": "Hãy suy nghĩ về Talking about hobbies.",
          "created_at": "2025-01-01T00:00:01.000Z"
        },
        {
          "title": "Choose the best answer: He ______ reading books in his free time. (A) like (B) likes (C) is like",
          "type": "multiple_choice",
          "points": 2,
          "question": "Choose the best answer: He ______ reading books in his free time. (A) like (B) likes (C) is like",
          "options": {
            "A": "Đáp án A",
            "B": "Đáp án B (Đúng)",
            "C": "Đáp án C",
            "D": "Đáp án D"
          },
          "correctOption": "B",
          "hint": "Hãy suy nghĩ về Talking about hobbies.",
          "created_at": "2025-01-01T00:00:02.000Z"
        },
        {
          "title": "Complete: She is good ______ drawing. (A) at (B) in (C) on",
          "type": "multiple_choice",
          "points": 2,
          "question": "Complete: She is good ______ drawing. (A) at (B) in (C) on",
          "options": {
            "A": "Đáp án A",
            "B": "Đáp án B (Đúng)",
            "C": "Đáp án C",
            "D": "Đáp án D"
          },
          "correctOption": "B",
          "hint": "Hãy suy nghĩ về Talking about hobbies.",
          "created_at": "2025-01-01T00:00:03.000Z"
        },
        {
          "title": "Choose: My hobby is ______ music. (A) listen to (B) listening to (C) to listen",
          "type": "multiple_choice",
          "points": 2,
          "question": "Choose: My hobby is ______ music. (A) listen to (B) listening to (C) to listen",
          "options": {
            "A": "Đáp án A",
            "B": "Đáp án B (Đúng)",
            "C": "Đáp án C",
            "D": "Đáp án D"
          },
          "correctOption": "B",
          "hint": "Hãy suy nghĩ về Talking about hobbies.",
          "created_at": "2025-01-01T00:00:04.000Z"
        },
        {
          "title": "Writing: Write a short paragraph (5–7 sentences) about your favourite hobby (what it is, when you do it, who you do it with, why you enjoy it).",
          "type": "essay",
          "points": 3,
          "question": "Writing: Write a short paragraph (5–7 sentences) about your favourite hobby (what it is, when you do it, who you do it with, why you enjoy it).",
          "hint": "Hãy viết về Talking about hobbies.",
          "answer": "Đây là câu trả lời mẫu về Talking about hobbies.",
          "created_at": "2025-01-01T00:00:05.000Z"
        },
        {
          "title": "Writing: Write about a hobby you would like to try and explain why it interests you.",
          "type": "essay",
          "points": 3,
          "question": "Writing: Write about a hobby you would like to try and explain why it interests you.",
          "hint": "Hãy viết về Talking about hobbies.",
          "answer": "Đây là câu trả lời mẫu về Talking about hobbies.",
          "created_at": "2025-01-01T00:00:06.000Z"
        }
      ]
    }
  ],
  "uuid": "39f01bf4-6508-4fc3-a7e2-58d05bb2cc8e"
}
